pybandit/__init__.py
pybandit-0.0.1.dist-info/LICENSE
pybandit-0.0.1.dist-info/WHEEL
pybandit-0.0.1.dist-info/METADATA
pybandit-0.0.1.dist-info/RECORD
